ilya_ezplot/__init__.py
ilya_ezplot/metric/cached_parameters_mixin.py
ilya_ezplot/metric/interpolate.py
ilya_ezplot/metric/metric.py
ilya_ezplot/plot/plot.py
ilya_ezplot/processing/momentum.py
ilya_ezplot/processing/running_avg.py
ilya_ezplot-0.11.dist-info/LICENSE
ilya_ezplot-0.11.dist-info/METADATA
ilya_ezplot-0.11.dist-info/WHEEL
ilya_ezplot-0.11.dist-info/top_level.txt
ilya_ezplot-0.11.dist-info/RECORD
