Metadata-Version: 2.1
Name: ilya-ezplot
Version: 0.11
Summary: Set of utilities for ploting results of non-deterministic experiments, e.g. machine learning, optimization, genetic algorithms.
Home-page: https://github.com/ikamensh/ilya_ezplot
Author: Ilya Kamenshchikov
Author-email: ikamenshchikov@gmail.com
License: UNKNOWN
Platform: UNKNOWN
Classifier: Programming Language :: Python :: 3
Classifier: License :: OSI Approved :: MIT License
Classifier: Operating System :: OS Independent
Requires-Python: >=3.6
Requires-Dist: numpy
Requires-Dist: matplotlib
